testing_sdk/__init__.py
testing_sdk/sdk.py
testing_sdk-0.0.4.dist-info/LICENCE.txt
testing_sdk-0.0.4.dist-info/METADATA
testing_sdk-0.0.4.dist-info/WHEEL
testing_sdk-0.0.4.dist-info/top_level.txt
testing_sdk-0.0.4.dist-info/RECORD
